fitsnap3/__init__.py
fitsnap3/__main__.py
fitsnap3/fitsnap.py
fitsnap3lib/__init__.py
fitsnap3lib/fitsnap.py
fitsnap3lib/initialize.py
fitsnap3lib/parallel_output.py
fitsnap3lib/parallel_tools.py
fitsnap3lib/calculators/__init__.py
fitsnap3lib/calculators/calculator.py
fitsnap3lib/calculators/calculator_factory.py
fitsnap3lib/calculators/lammps_base.py
fitsnap3lib/calculators/lammps_custom.py
fitsnap3lib/calculators/lammps_pace.py
fitsnap3lib/calculators/lammps_snap.py
fitsnap3lib/io/__init__.py
fitsnap3lib/io/error.py
fitsnap3lib/io/input.py
fitsnap3lib/io/output.py
fitsnap3lib/io/outputs/__init__.py
fitsnap3lib/io/outputs/custom.py
fitsnap3lib/io/outputs/output_factory.py
fitsnap3lib/io/outputs/outputs.py
fitsnap3lib/io/outputs/pace.py
fitsnap3lib/io/outputs/snap.py
fitsnap3lib/io/outputs/template_output.py
fitsnap3lib/io/sections/__init__.py
fitsnap3lib/io/sections/eshift.py
fitsnap3lib/io/sections/extras.py
fitsnap3lib/io/sections/groups.py
fitsnap3lib/io/sections/memory.py
fitsnap3lib/io/sections/outfile.py
fitsnap3lib/io/sections/path.py
fitsnap3lib/io/sections/reference.py
fitsnap3lib/io/sections/scraper.py
fitsnap3lib/io/sections/section_factory.py
fitsnap3lib/io/sections/sections.py
fitsnap3lib/io/sections/template.py
fitsnap3lib/io/sections/trainshift.py
fitsnap3lib/io/sections/calculator_sections/__init__.py
fitsnap3lib/io/sections/calculator_sections/ace.py
fitsnap3lib/io/sections/calculator_sections/basic_calculator.py
fitsnap3lib/io/sections/calculator_sections/bispectrum.py
fitsnap3lib/io/sections/calculator_sections/calculator.py
fitsnap3lib/io/sections/calculator_sections/custom.py
fitsnap3lib/io/sections/solver_sections/__init__.py
fitsnap3lib/io/sections/solver_sections/ard.py
fitsnap3lib/io/sections/solver_sections/jax.py
fitsnap3lib/io/sections/solver_sections/lasso.py
fitsnap3lib/io/sections/solver_sections/network.py
fitsnap3lib/io/sections/solver_sections/pytorch.py
fitsnap3lib/io/sections/solver_sections/ridge.py
fitsnap3-3.1.0.4.dist-info/LICENSE
fitsnap3-3.1.0.4.dist-info/METADATA
fitsnap3-3.1.0.4.dist-info/WHEEL
fitsnap3-3.1.0.4.dist-info/top_level.txt
fitsnap3-3.1.0.4.dist-info/RECORD
