Metadata-Version: 2.1
Name: fitsnap3
Version: 3.1.0.4
Summary: Molecular Machine Learning Interface
Author-email: Drew Rohskopf <adrohsk@sandia.gov>
Maintainer-email: Drew Rohskopf <adrohsk@sandia.gov>
License: GNU GENERAL PUBLIC LICENSE
Project-URL: repository, https://github.com/FitSNAP/FitSNAP
Project-URL: documentation, https://fitsnap.github.io/
Classifier: Programming Language :: Python :: 3
Classifier: License :: OSI Approved :: MIT License
Classifier: Operating System :: OS Independent
Requires-Python: >=3.9.0
License-File: LICENSE
Requires-Dist: numpy
Requires-Dist: scipy
Requires-Dist: scikit-learn
Requires-Dist: virtualenv
Requires-Dist: psutil
Requires-Dist: pandas
Requires-Dist: tabulate
Requires-Dist: mpi4py
Requires-Dist: Cython
Requires-Dist: torch
Requires-Dist: sympy
Requires-Dist: pyyaml
